Workbook

Sheet Cómo usar
B1: Máquina de leads Nexvore
B2: Tiendas de IG/TikTok con 1.500–40.000 seguidores, stock físico y sin tienda web propia.
B4: Rutina diaria (noche anterior, 20 min)
B5: 1. Elige 1 segmento en la pestaña 'Segmentos' (rota: un segmento por día).
B6: 2. Abre 'Palabras clave', filtra por ese segmento y toma 3–5 palabras con estado 'Pendiente'.
B7: 3. Busca cada palabra en su plataforma. Las de tipo 'Google' se pegan tal cual en Google (encuentran perfiles con número o 'envíos a todo Chile' en la bio).
B8: 4. Por cada cuenta que cumpla el filtro, agrega una fila en 'Leads'. La columna 'En rango' se marca sola (1.500–40.000 seguidores).
B9: 5. En cada perfil que sirva, toca 'Sugerencias para ti' → cada cuenta buena trae 5–10 parecidas.
B10: 6. Anota 'Cosa 1' y 'Cosa 2' (lo que mejorarías) → son el mensaje del día siguiente (ver 01-prospeccion.md).
B11: 7. Marca la palabra clave como 'Usada' y anota cuántos leads dio. Las que más dan, se repiten.
B13: Filtro de un lead (las 4 obligatorias)
B14: • 1.500 a 40.000 seguidores · • Vende producto físico con stock · • Sin tienda web o con una mala (link a WhatsApp/Linktree/nada) · • Publicó en los últimos 14 días
... B19: Meta: 100 leads nuevos por semana en la planilla → 100 contactos enviados al día sale de aquí.

Sheet Resumen
A1: Resumen del embudo
A2: Se calcula solo desde 'Leads' y 'Palabras clave'. No editar.
A4: Segmento | B4: Leads | C4: En rango | D4: Por revisar | E4: Por contactar | F4: Enviado | G4: Respondió | H4: Reunión | I4: Cerrado
A5: S1 Moda luxury hombre | B5: =COUNTIFS(Leads!$E$2:$E$201,"S1",Leads!$A$2:$A$201,"<>EJEMPLO") | C5: =COUNTIFS(Leads!$E$2:$E$201,"S1",Leads!$G$2:$G$201,"Sí",Leads!$A$2:$A$201,"<>EJEMPLO") | D5: =COUNTIFS(Leads!$E$2:$E$201,"S1",Leads!$M$2:$M$201,"Por revisar",Leads!$A$2:$A$201,"<>EJEMPLO") | E5: =COUNTIFS(Leads!$E$2:$E$201,"S1",Leads!$M$2:$M$201,"Por contactar",Leads!$A$2:$A$201,"<>EJEMPLO") | F5: =COUNTIFS(Leads!$E$2:$E$201,"S1",Leads!$M$2:$M$201,"Enviado",Leads!$A$2:$A$201,"<>EJEMPLO") | G5: =COUNTIFS(Leads!$E$2:$E$201,"S1",Leads!$M$2:$M$201,"Respondió",Leads!$A$2:$A$201,"<>EJEMPLO") | H5: =COUNTIFS(Leads!$E$2:$E$201,"S1",Leads!$M$2:$M$201,"Reunión",Leads!$A$2:$A$201,"<>EJEMPLO") | I5: =COUNTIFS(Leads!$E$2:$E$201,"S1",Leads!$M$2:$M$201,"Cerrado",Leads!$A$2:$A$201,"<>EJEMPLO")
A6: S2 Sneakers | B6: =COUNTIFS(Leads!$E$2:$E$201,"S2",Leads!$A$2:$A$201,"<>EJEMPLO") | C6: =COUNTIFS(Leads!$E$2:$E$201,"S2",Leads!$G$2:$G$201,"Sí",Leads!$A$2:$A$201,"<>EJEMPLO") | D6: =COUNTIFS(Leads!$E$2:$E$201,"S2",Leads!$M$2:$M$201,"Por revisar",Leads!$A$2:$A$201,"<>EJEMPLO") | E6: =COUNTIFS(Leads!$E$2:$E$201,"S2",Leads!$M$2:$M$201,"Por contactar",Leads!$A$2:$A$201,"<>EJEMPLO") | F6: =COUNTIFS(Leads!$E$2:$E$201,"S2",Leads!$M$2:$M$201,"Enviado",Leads!$A$2:$A$201,"<>EJEMPLO") | G6: =COUNTIFS(Leads!$E$2:$E$201,"S2",Leads!$M$2:$M$201,"Respondió",Leads!$A$2:$A$201,"<>EJEMPLO") | H6: =COUNTIFS(Leads!$E$2:$E$201,"S2",Leads!$M$2:$M$201,"Reunión",Leads!$A$2:$A$201,"<>EJEMPLO") | I6: =COUNTIFS(Leads!$E$2:$E$201,"S2",Leads!$M$2:$M$201,"Cerrado",Leads!$A$2:$A$201,"<>EJEMPLO")
A7: S3 Botas mujer | B7: =COUNTIFS(Leads!$E$2:$E$201,"S3",Leads!$A$2:$A$201,"<>EJEMPLO") | C7: =COUNTIFS(Leads!$E$2:$E$201,"S3",Leads!$G$2:$G$201,"Sí",Leads!$A$2:$A$201,"<>EJEMPLO") | D7: =COUNTIFS(Leads!$E$2:$E$201,"S3",Leads!$M$2:$M$201,"Por revisar",Leads!$A$2:$A$201,"<>EJEMPLO") | E7: =COUNTIFS(Leads!$E$2:$E$201,"S3",Leads!$M$2:$M$201,"Por contactar",Leads!$A$2:$A$201,"<>EJEMPLO") | F7: =COUNTIFS(Leads!$E$2:$E$201,"S3",Leads!$M$2:$M$201,"Enviado",Leads!$A$2:$A$201,"<>EJEMPLO") | G7: =COUNTIFS(Leads!$E$2:$E$201,"S3",Leads!$M$2:$M$201,"Respondió",Leads!$A$2:$A$201,"<>EJEMPLO") | H7: =COUNTIFS(Leads!$E$2:$E$201,"S3",Leads!$M$2:$M$201,"Reunión",Leads!$A$2:$A$201,"<>EJEMPLO") | I7: =COUNTIFS(Leads!$E$2:$E$201,"S3",Leads!$M$2:$M$201,"Cerrado",Leads!$A$2:$A$201,"<>EJEMPLO")
A8: S4 Faldas / fiesta | B8: =COUNTIFS(Leads!$E$2:$E$201,"S4",Leads!$A$2:$A$201,"<>EJEMPLO") | C8: =COUNTIFS(Leads!$E$2:$E$201,"S4",Leads!$G$2:$G$201,"Sí",Leads!$A$2:$A$201,"<>EJEMPLO") | D8: =COUNTIFS(Leads!$E$2:$E$201,"S4",Leads!$M$2:$M$201,"Por revisar",Leads!$A$2:$A$201,"<>EJEMPLO") | E8: =COUNTIFS(Leads!$E$2:$E$201,"S4",Leads!$M$2:$M$201,"Por contactar",Leads!$A$2:$A$201,"<>EJEMPLO") | F8: =COUNTIFS(Leads!$E$2:$E$201,"S4",Leads!$M$2:$M$201,"Enviado",Leads!$A$2:$A$201,"<>EJEMPLO") | G8: =COUNTIFS(Leads!$E$2:$E$201,"S4",Leads!$M$2:$M$201,"Respondió",Leads!$A$2:$A$201,"<>EJEMPLO") | H8: =COUNTIFS(Leads!$E$2:$E$201,"S4",Leads!$M$2:$M$201,"Reunión",Leads!$A$2:$A$201,"<>EJEMPLO") | I8: =COUNTIFS(Leads!$E$2:$E$201,"S4",Leads!$M$2:$M$201,"Cerrado",Leads!$A$2:$A$201,"<>EJEMPLO")
A9: S5 Boutiques mujer | B9: =COUNTIFS(Leads!$E$2:$E$201,"S5",Leads!$A$2:$A$201,"<>EJEMPLO") | C9: =COUNTIFS(Leads!$E$2:$E$201,"S5",Leads!$G$2:$G$201,"Sí",Leads!$A$2:$A$201,"<>EJEMPLO") | D9: =COUNTIFS(Leads!$E$2:$E$201,"S5",Leads!$M$2:$M$201,"Por revisar",Leads!$A$2:$A$201,"<>EJEMPLO") | E9: =COUNTIFS(Leads!$E$2:$E$201,"S5",Leads!$M$2:$M$201,"Por contactar",Leads!$A$2:$A$201,"<>EJEMPLO") | F9: =COUNTIFS(Leads!$E$2:$E$201,"S5",Leads!$M$2:$M$201,"Enviado",Leads!$A$2:$A$201,"<>EJEMPLO") | G9: =COUNTIFS(Leads!$E$2:$E$201,"S5",Leads!$M$2:$M$201,"Respondió",Leads!$A$2:$A$201,"<>EJEMPLO") | H9: =COUNTIFS(Leads!$E$2:$E$201,"S5",Leads!$M$2:$M$201,"Reunión",Leads!$A$2:$A$201,"<>EJEMPLO") | I9: =COUNTIFS(Leads!$E$2:$E$201,"S5",Leads!$M$2:$M$201,"Cerrado",Leads!$A$2:$A$201,"<>EJEMPLO")
A10: Total | B10: =SUM(B5:B9) | C10: =SUM(C5:C9) | D10: =SUM(D5:D9) | E10: =SUM(E5:E9) | F10: =SUM(F5:F9) | G10: =SUM(G5:G9) | H10: =SUM(H5:H9) | I10: =SUM(I5:I9)
A12: Tasa de respuesta (respondió o más / enviados) | B12: =IFERROR((G10+H10+I10)/(F10+G10+H10+I10),0)
A13: Reuniones sobre respuestas | B13: =IFERROR((H10+I10)/(G10+H10+I10),0)
A14: Palabras clave usadas / total | B14: =COUNTIF('Palabras clave'!E2:E88,"<>Pendiente")&" / "&COUNTA('Palabras clave'!D2:D88)

Sheet Segmentos
A1: ID | B1: Segmento | C1: Qué venden | D1: Quién les compra | E1: Qué necesita ese comprador | F1: Ángulo de venta por cantidad | G1: Oferta ejemplo para su web | H1: Prioridad
A2: S1 | B2: Moda luxury hombre (reventa marcas premium) | C2: EA7, Emporio Armani, Hugo Boss, Calvin Klein, Lacoste, Polo Ralph Lauren, Nike Tech, Moschino | D2: Hombres 18–35 que compran online y quieren marca original | E2: Garantía de original, tallas claras, ver stock real sin preguntar por DM, envío rápido | F2: Conjunto completo (polerón + pantalón) o 3 poleras de distintos colores | G2: 'Pack 3 poleras EA7' con descuento + envío gratis sobre $60.000 | H2: A
A3: S2 | B3: Sneakers originales (reventa / permuta) | C3: Jordan, Nike Dunk, New Balance, Vans, Yeezy | D3: Hombres y mujeres 16–35, coleccionistas y fans del streetwear | E3: Autenticidad, talla exacta en cm, fotos reales, pago en abonos | F3: Zapatilla + accesorio (calcetines, gorro, limpiador) o 2 pares | G3: Combo zapatilla + kit de limpieza; abono con reserva | H3: A
A4: S3 | B4: Botas mujer para salir / carrete | C4: Botas caña alta, texanas, plataforma, bucaneras, botines | D4: Mujeres 18–30 que salen de fiesta y compran por Reels/TikTok | E4: Talla y altura de caña, cómo calza, que llegue antes del finde, combinar con outfit | F4: Mismo modelo en 2 colores, o bota + falda/top (outfit completo) | G4: 'Lleva 2 pares y el segundo con 15%' + guía de tallas en cm | H4: A
A5: S4 | B5: Faldas y outfits de fiesta mujer | C5: Faldas mini, vestidos, tops, bodies, conjuntos | D5: Mujeres 18–30 que arman outfit para salir | E5: Ver el outfit completo, tallas, colores, envío rápido | F5: Outfit completo (falda + top + bota) o 3 prendas a precio pack | G5: 'Arma tu outfit: 3 prendas por $X' | H5: B
A6: S5 | B6: Boutiques mujer (moda general) | C6: Ropa mujer variada, temporada, básicos | D6: Mujeres 20–45 | E6: Probar tallas, cambios, ver todo el catálogo | F6: Básicos x3 (poleras, calzas) y packs de temporada | G6: '3 básicos por $X' + colección por temporada | H6: B

Sheet Palabras clave
A1: Segmento | B1: Plataforma | C1: Tipo | D1: Palabra clave / búsqueda | E1: Estado | F1: Leads encontrados | G1: Notas
A2: S1 | B2: Instagram | C2: Hashtag | D2: #ropaoriginalchile | E2: Pendiente
A3: S1 | B3: Instagram | C3: Hashtag | D3: #ropademarcachile | E3: Pendiente
A4: S1 | B4: Instagram | C4: Hashtag | D4: #ea7chile | E4: Pendiente
A5: S1 | B5: Instagram | C5: Hashtag | D5: #emporioarmanichile | E5: Pendiente
A6: S1 | B6: Instagram | C6: Hashtag | D6: #hugobosschile | E6: Pendiente
A7: S1 | B7: Instagram | C7: Hashtag | D7: #calvinkleinchile | E7: Pendiente
A8: S1 | B8: Instagram | C8: Hashtag | D8: #lacostechile | E8: Pendiente
A9: S1 | B9: Instagram | C9: Hashtag | D9: #poloralphlaurenchile | E9: Pendiente
A10: S1 | B10: Instagram | C10: Hashtag | D10: #niketechchile | E10: Pendiente
A11: S1 | B11: Instagram | C11: Hashtag | D11: #outfithombrechile | E11: Pendiente
A12: S1 | B12: Instagram | C12: Hashtag | D12: #modamasculinachile | E12: Pendiente
A13: S1 | B13: Instagram | C13: Búsqueda | D13: ropa original chile | E13: Pendiente
... A88: S5 | B88: Google | C88: Operador | D88: site:instagram.com "tienda de ropa" "solo por DM" Chile | E88: Pendiente

Sheet Leads
A1: Fecha | B1: Cuenta (@) | C1: Link | D1: Red | E1: Segmento | F1: Seguidores | G1: En rango (1.500–40.000) | H1: Tiene web | I1: WhatsApp en bio | J1: Palabra clave de origen | K1: Cosa 1 a mejorar | L1: Cosa 2 a mejorar | M1: Estado | N1: Próximo seguimiento | O1: Notas
A2: EJEMPLO | B2: @tienda_ejemplo | C2: https://instagram.com/tienda_ejemplo | D2: IG | E2: S3 | F2: 8200 | G2: =IF(F2="","",IF(AND(F2>=1500,F2<=40000),"Sí","No")) | H2: No | I2: +56 9 XXXX XXXX | J2: #botaschile | K2: Tallas se preguntan en comentarios | L2: El video vende pero no hay dónde comprar | M2: Por contactar | N2: =IF(OR(A2="",A2="EJEMPLO"),"",IF(M2="Enviado",DATEVALUE(A2)+2,"")) | O2: Fila de ejemplo: bórrala al empezar
A3: 2026-09-26 | B3: @lider_en_marcas_2 | C3: https://instagram.com/lider_en_marcas_2 | D3: IG | E3: S1 | F3: 13000 | G3: =IF(F3="","",IF(AND(F3>=1500,F3<=40000),"Sí","No")) | H3: No | K3: Ventas solo por DM | L3: Sin packs por cantidad | M3: Reunión | N3: =IF(OR(A3="",A3="EJEMPLO"),"",IF(M3="Enviado",DATEVALUE(A3)+2,"")) | O3: Reunión mié 30-sep
B4: @tincho.exclusiveog | C4: https://instagram.com/tincho.exclusiveog | D4: IG | E4: S1 | G4: =IF(F4="","",IF(AND(F4>=1500,F4<=40000),"Sí","No")) | J4: Referencia de Mateo | M4: Por contactar | N4: =IF(OR(A4="",A4="EJEMPLO"),"",IF(M4="Enviado",DATEVALUE(A4)+2,"")) | O4: Completar seguidores
B5: @padres.market | C5: https://instagram.com/padres.market | D5: IG | E5: S1 | F5: 7460 | G5: =IF(F5="","",IF(AND(F5>=1500,F5<=40000),"Sí","No")) | H5: No | J5: Referencia de Mateo | K5: Stock solo en historias 'Disponible' | L5: 'En camino' podría ser preventa | M5: Por contactar | N5: =IF(OR(A5="",A5="EJEMPLO"),"",IF(M5="Enviado",DATEVALUE(A5)+2,"")) | O5: Prioridad A
B6: @19markett | C6: https://instagram.com/19markett | D6: IG | E6: S2 | F6: 11700 | G6: =IF(F6="","",IF(AND(F6>=1500,F6<=40000),"Sí","No")) | H6: No | J6: Referencia de Mateo | K6: Sin link para comprar directo | L6: Clientes de feria sin dónde recomprar | M6: Por contactar | N6: =IF(OR(A6="",A6="EJEMPLO"),"",IF(M6="Enviado",DATEVALUE(A6)+2,"")) | O6: Prioridad A. Stand en ferias
B7: @ogfleece.cl | C7: https://instagram.com/ogfleece.cl | D7: IG | E7: S1 | F7: 5625 | G7: =IF(F7="","",IF(AND(F7>=1500,F7<=40000),"Sí","No")) | H7: Mala | J7: Referencia de Mateo | K7: Link lleva a grupo de WhatsApp | L7: Desde Chiloé: web abre todo Chile | M7: Por contactar | N7: =IF(OR(A7="",A7="EJEMPLO"),"",IF(M7="Enviado",DATEVALUE(A7)+2,"")) | O7: Prioridad A-
B8: @gengar.market | C8: https://instagram.com/gengar.market | D8: IG | E8: S2 | F8: 14900 | G8: =IF(F8="","",IF(AND(F8>=1500,F8<=40000),"Sí","No")) | H8: Sí | J8: Referencia de Mateo | K8: Stock en historias pese a tener web | L8: Revisar gengarmarket.cl | M8: Por contactar | N8: =IF(OR(A8="",A8="EJEMPLO"),"",IF(M8="Enviado",DATEVALUE(A8)+2,"")) | O8: Prioridad B. Perfil privado
B9: @kicksfresh.cl | C9: https://instagram.com/kicksfresh.cl | D9: IG | E9: S2 | G9: =IF(F9="","",IF(AND(F9>=1500,F9<=40000),"Sí","No")) | J9: Sugerencias de gengar.market | M9: Por revisar | N9: =IF(OR(A9="",A9="EJEMPLO"),"",IF(M9="Enviado",DATEVALUE(A9)+2,""))
B10: @grassneakers._ | C10: https://instagram.com/grassneakers._ | D10: IG | E10: S2 | G10: =IF(F10="","",IF(AND(F10>=1500,F10<=40000),"Sí","No")) | J10: Sugerencias de gengar.market | M10: Por revisar | N10: =IF(OR(A10="",A10="EJEMPLO"),"",IF(M10="Enviado",DATEVALUE(A10)+2,""))
G11: =IF(F11="","",IF(AND(F11>=1500,F11<=40000),"Sí","No")) | N11: =IF(OR(A11="",A11="EJEMPLO"),"",IF(M11="Enviado",DATEVALUE(A11)+2,""))
G12: =IF(F12="","",IF(AND(F12>=1500,F12<=40000),"Sí","No")) | N12: =IF(OR(A12="",A12="EJEMPLO"),"",IF(M12="Enviado",DATEVALUE(A12)+2,""))
G13: =IF(F13="","",IF(AND(F13>=1500,F13<=40000),"Sí","No")) | N13: =IF(OR(A13="",A13="EJEMPLO"),"",IF(M13="Enviado",DATEVALUE(A13)+2,""))
G14: =IF(F14="","",IF(AND(F14>=1500,F14<=40000),"Sí","No")) | N14: =IF(OR(A14="",A14="EJEMPLO"),"",IF(M14="Enviado",DATEVALUE(A14)+2,""))
G15: =IF(F15="","",IF(AND(F15>=1500,F15<=40000),"Sí","No")) | N15: =IF(OR(A15="",A15="EJEMPLO"),"",IF(M15="Enviado",DATEVALUE(A15)+2,""))
G16: =IF(F16="","",IF(AND(F16>=1500,F16<=40000),"Sí","No")) | N16: =IF(OR(A16="",A16="EJEMPLO"),"",IF(M16="Enviado",DATEVALUE(A16)+2,""))
G17: =IF(F17="","",IF(AND(F17>=1500,F17<=40000),"Sí","No")) | N17: =IF(OR(A17="",A17="EJEMPLO"),"",IF(M17="Enviado",DATEVALUE(A17)+2,""))
G18: =IF(F18="","",IF(AND(F18>=1500,F18<=40000),"Sí","No")) | N18: =IF(OR(A18="",A18="EJEMPLO"),"",IF(M18="Enviado",DATEVALUE(A18)+2,""))
G19: =IF(F19="","",IF(AND(F19>=1500,F19<=40000),"Sí","No")) | N19: =IF(OR(A19="",A19="EJEMPLO"),"",IF(M19="Enviado",DATEVALUE(A19)+2,""))
G20: =IF(F20="","",IF(AND(F20>=1500,F20<=40000),"Sí","No")) | N20: =IF(OR(A20="",A20="EJEMPLO"),"",IF(M20="Enviado",DATEVALUE(A20)+2,""))
G21: =IF(F21="","",IF(AND(F21>=1500,F21<=40000),"Sí","No")) | N21: =IF(OR(A21="",A21="EJEMPLO"),"",IF(M21="Enviado",DATEVALUE(A21)+2,""))
G22: =IF(F22="","",IF(AND(F22>=1500,F22<=40000),"Sí","No")) | N22: =IF(OR(A22="",A22="EJEMPLO"),"",IF(M22="Enviado",DATEVALUE(A22)+2,""))
... G201: =IF(F201="","",IF(AND(F201>=1500,F201<=40000),"Sí","No")) | N201: =IF(OR(A201="",A201="EJEMPLO"),"",IF(M201="Enviado",DATEVALUE(A201)+2,""))
